settle.cpython-38-darwin.so
pySettle/__init__.py
pySettle/settler.py
pySettle-1.3.0.dist-info/LICENSE
pySettle-1.3.0.dist-info/METADATA
pySettle-1.3.0.dist-info/WHEEL
pySettle-1.3.0.dist-info/top_level.txt
pySettle-1.3.0.dist-info/RECORD
