Metadata-Version: 2.1
Name: pySettle
Version: 1.3.0
Summary: Computes ignition conditions for Type I X-ray bursts                 using a multi-zone model of the Neutron star accreting layer
Author: Andrew Cumming
Author-email: andrew.cumming@mcgill.ca
License: MIT
Keywords: settle
Classifier: Development Status :: 3 - Alpha
Classifier: Intended Audience :: Developers
Classifier: License :: OSI Approved :: MIT License
Classifier: Natural Language :: English
Classifier: Programming Language :: Python :: 3.6
Classifier: Programming Language :: Python :: 3.7
Classifier: Programming Language :: Python :: 3.8
Classifier: Programming Language :: Python :: 3.9
Classifier: Programming Language :: Python :: 3.10
Classifier: Programming Language :: Python :: 3.11
Requires-Python: >=3.6
License-File: LICENSE
Requires-Dist: numpy >=1.16
